{"name": ".223 Remington BERGER 73GR  BT BERGER 73GR  BT", "productName": "223 Remington 73 Grain Boat Tail Target Rifle Ammunition", "caliber": "5.56mm NATO / 5.56x45 / 223 Remington", "bulletType": "Boat Tail Target", "bulletVendor": "Berger", "cartridge": "BERGER 73GR  BT", "cartridgeVendor": "Berger", "url": "https://bergerbullets.com/product/223-remington-73-grain-boat-tail-target/", "country": "USA", "bc": 0.348, "g7": 0.178, "weight": 73, "muzzleVelocity": 859, "author": null, "note": null, "extra": null}